genderdefiner/__init__.py
genderdefiner/enums.py
genderdefiner/genderdefiner.py
genderdefiner/types.py
gender_definer-0.0.3.dist-info/METADATA
gender_definer-0.0.3.dist-info/WHEEL
gender_definer-0.0.3.dist-info/RECORD
